{
  "image": "05.png",
  "instances": [
    {
      "instance_id": 1,
      "class_id": 2,
      "class_name": "Type_3",
      "score": 0.9460982084274292,
      "source": "teacher+classical",
      "box": [
        677,
        737,
        811,
        925
      ],
      "area": 17587,
      "polygons": [
        [
          677.0,
          737.0,
          677.0,
          741.0,
          690.0,
          746.0,
          698.0,
          754.0,
          695.0,
          762.0,
          685.0,
          771.0,
          693.0,
          779.0,
          693.0,
          785.0,
          677.0,
          792.0,
          677.0,
          923.0,
          753.0,
          922.0,
          759.0,
          919.0,
          778.0,
          918.0,
          806.0,
          911.0,
          809.0,
          908.0,
          810.0,
          900.0,
          802.0,
          894.0,
          785.0,
          890.0,
          783.0,
          884.0,
          787.0,
          880.0,
          789.0,
          872.0,
          795.0,
          872.0,
          799.0,
          869.0,
          808.0,
          875.0,
          808.0,
          870.0,
          795.0,
          858.0,
          763.0,
          852.0,
          763.0,
          847.0,
          760.0,
          845.0,
          759.0,
          836.0,
          763.0,
          834.0,
          775.0,
          841.0,
          772.0,
          845.0,
          779.0,
          850.0,
          782.0,
          848.0,
          778.0,
          843.0,
          782.0,
          838.0,
          780.0,
          833.0,
          782.0,
          826.0,
          778.0,
          823.0,
          781.0,
          817.0,
          778.0,
          813.0,
          780.0,
          806.0,
          777.0,
          803.0,
          779.0,
          787.0,
          776.0,
          784.0,
          778.0,
          778.0,
          773.0,
          762.0,
          768.0,
          761.0,
          764.0,
          765.0,
          750.0,
          759.0,
          752.0,
          753.0,
          746.0,
          750.0,
          738.0,
          754.0,
          727.0,
          748.0,
          727.0,
          737.0
        ]
      ]
    },
    {
      "instance_id": 2,
      "class_id": 2,
      "class_name": "Type_3",
      "score": 0.9351096749305725,
      "source": "teacher+classical",
      "box": [
        266,
        632,
        470,
        788
      ],
      "area": 24923,
      "polygons": [
        [
          420.0,
          639.0,
          410.0,
          632.0,
          397.0,
          632.0,
          380.0,
          638.0,
          368.0,
          649.0,
          351.0,
          647.0,
          347.0,
          643.0,
          338.0,
          648.0,
          328.0,
          644.0,
          320.0,
          647.0,
          307.0,
          641.0,
          290.0,
          644.0,
          275.0,
          651.0,
          266.0,
          651.0,
          266.0,
          710.0,
          286.0,
          712.0,
          286.0,
          717.0,
          279.0,
          722.0,
          278.0,
          727.0,
          266.0,
          728.0,
          266.0,
          787.0,
          280.0,
          787.0,
          284.0,
          783.0,
          288.0,
          787.0,
          290.0,
          784.0,
          283.0,
          782.0,
          285.0,
          771.0,
          294.0,
          769.0,
          298.0,
          773.0,
          301.0,
          771.0,
          305.0,
          774.0,
          306.0,
          767.0,
          310.0,
          764.0,
          315.0,
          769.0,
          312.0,
          777.0,
          318.0,
          780.0,
          328.0,
          780.0,
          332.0,
          784.0,
          338.0,
          780.0,
          337.0,
          767.0,
          343.0,
          757.0,
          355.0,
          759.0,
          356.0,
          787.0,
          443.0,
          787.0,
          440.0,
          773.0,
          444.0,
          770.0,
          458.0,
          787.0,
          469.0,
          787.0,
          469.0,
          740.0,
          462.0,
          743.0,
          452.0,
          734.0,
          454.0,
          715.0,
          451.0,
          705.0,
          445.0,
          698.0,
          436.0,
          665.0
        ]
      ]
    },
    {
      "instance_id": 3,
      "class_id": 3,
      "class_name": "Type_4",
      "score": 0.9010219573974609,
      "source": "teacher+classical",
      "box": [
        422,
        684,
        652,
        842
      ],
      "area": 24872,
      "polygons": [
        [
          648.0,
          684.0,
          568.0,
          684.0,
          568.0,
          693.0,
          560.0,
          702.0,
          556.0,
          702.0,
          548.0,
          709.0,
          535.0,
          715.0,
          528.0,
          715.0,
          512.0,
          724.0,
          486.0,
          731.0,
          473.0,
          727.0,
          469.0,
          730.0,
          466.0,
          728.0,
          457.0,
          730.0,
          451.0,
          702.0,
          443.0,
          707.0,
          441.0,
          715.0,
          436.0,
          718.0,
          429.0,
          715.0,
          422.0,
          706.0,
          422.0,
          813.0,
          460.0,
          827.0,
          468.0,
          822.0,
          474.0,
          831.0,
          491.0,
          834.0,
          501.0,
          841.0,
          533.0,
          841.0,
          533.0,
          822.0,
          517.0,
          817.0,
          511.0,
          810.0,
          511.0,
          804.0,
          518.0,
          798.0,
          522.0,
          800.0,
          522.0,
          806.0,
          527.0,
          807.0,
          529.0,
          811.0,
          533.0,
          811.0,
          536.0,
          815.0,
          539.0,
          813.0,
          543.0,
          817.0,
          552.0,
          815.0,
          555.0,
          821.0,
          558.0,
          820.0,
          563.0,
          824.0,
          567.0,
          821.0,
          591.0,
          824.0,
          603.0,
          822.0,
          620.0,
          828.0,
          624.0,
          818.0,
          630.0,
          814.0,
          651.0,
          821.0,
          651.0,
          804.0,
          641.0,
          803.0,
          634.0,
          796.0,
          635.0,
          776.0,
          639.0,
          771.0,
          629.0,
          756.0,
          630.0,
          747.0,
          638.0,
          745.0,
          647.0,
          734.0
        ]
      ]
    },
    {
      "instance_id": 4,
      "class_id": 0,
      "class_name": "Type_1",
      "score": 0.8882208466529846,
      "source": "teacher+classical",
      "box": [
        566,
        977,
        703,
        1102
      ],
      "area": 11242,
      "polygons": [
        [
          697.0,
          982.0,
          689.0,
          977.0,
          679.0,
          980.0,
          666.0,
          989.0,
          663.0,
          987.0,
          658.0,
          988.0,
          641.0,
          980.0,
          638.0,
          981.0,
          631.0,
          979.0,
          627.0,
          983.0,
          623.0,
          981.0,
          619.0,
          984.0,
          618.0,
          983.0,
          611.0,
          986.0,
          605.0,
          993.0,
          596.0,
          996.0,
          585.0,
          990.0,
          584.0,
          998.0,
          581.0,
          1000.0,
          569.0,
          991.0,
          566.0,
          991.0,
          566.0,
          1101.0,
          624.0,
          1101.0,
          626.0,
          1090.0,
          632.0,
          1086.0,
          651.0,
          1086.0,
          660.0,
          1083.0,
          665.0,
          1085.0,
          670.0,
          1084.0,
          673.0,
          1086.0,
          680.0,
          1085.0,
          681.0,
          1081.0,
          673.0,
          1070.0,
          673.0,
          1066.0,
          664.0,
          1051.0,
          664.0,
          1041.0,
          661.0,
          1039.0,
          661.0,
          1037.0,
          670.0,
          1031.0,
          674.0,
          1033.0,
          674.0,
          1028.0,
          678.0,
          1025.0,
          687.0,
          1030.0,
          688.0,
          1029.0,
          687.0,
          1023.0,
          690.0,
          1019.0,
          694.0,
          1018.0,
          692.0,
          1014.0,
          702.0,
          1005.0,
          702.0,
          994.0,
          700.0,
          992.0,
          701.0,
          988.0
        ]
      ]
    },
    {
      "instance_id": 5,
      "class_id": 3,
      "class_name": "Type_4",
      "score": 0.8873444199562073,
      "source": "teacher+classical",
      "box": [
        438,
        974,
        628,
        1169
      ],
      "area": 26015,
      "polygons": [
        [
          627.0,
          991.0,
          611.0,
          991.0,
          594.0,
          996.0,
          566.0,
          977.0,
          560.0,
          977.0,
          556.0,
          984.0,
          549.0,
          984.0,
          541.0,
          993.0,
          535.0,
          991.0,
          536.0,
          987.0,
          542.0,
          985.0,
          539.0,
          982.0,
          518.0,
          982.0,
          504.0,
          974.0,
          501.0,
          981.0,
          497.0,
          978.0,
          493.0,
          982.0,
          485.0,
          983.0,
          475.0,
          977.0,
          461.0,
          981.0,
          457.0,
          1000.0,
          466.0,
          1009.0,
          463.0,
          1013.0,
          457.0,
          1010.0,
          463.0,
          1016.0,
          459.0,
          1021.0,
          461.0,
          1026.0,
          447.0,
          1034.0,
          438.0,
          1044.0,
          438.0,
          1168.0,
          501.0,
          1168.0,
          500.0,
          1162.0,
          492.0,
          1154.0,
          498.0,
          1138.0,
          516.0,
          1128.0,
          530.0,
          1126.0,
          552.0,
          1117.0,
          556.0,
          1119.0,
          555.0,
          1123.0,
          548.0,
          1127.0,
          545.0,
          1125.0,
          541.0,
          1130.0,
          538.0,
          1128.0,
          537.0,
          1133.0,
          532.0,
          1132.0,
          512.0,
          1142.0,
          517.0,
          1141.0,
          523.0,
          1147.0,
          534.0,
          1142.0,
          538.0,
          1145.0,
          542.0,
          1142.0,
          553.0,
          1144.0,
          557.0,
          1139.0,
          566.0,
          1147.0,
          580.0,
          1143.0,
          604.0,
          1143.0,
          609.0,
          1135.0,
          605.0,
          1116.0,
          610.0,
          1113.0,
          605.0,
          1101.0,
          613.0,
          1089.0,
          603.0,
          1082.0,
          599.0,
          1076.0,
          600.0,
          1070.0,
          593.0,
          1069.0,
          593.0,
          1064.0,
          588.0,
          1062.0,
          586.0,
          1048.0,
          593.0,
          1040.0,
          604.0,
          1045.0,
          607.0,
          1040.0,
          605.0,
          1031.0,
          615.0,
          1023.0,
          623.0,
          1026.0,
          627.0,
          1022.0
        ]
      ]
    },
    {
      "instance_id": 6,
      "class_id": 3,
      "class_name": "Type_4",
      "score": 0.8656938672065735,
      "source": "teacher+classical",
      "box": [
        510,
        1034,
        691,
        1170
      ],
      "area": 16536,
      "polygons": [
        [
          510.0,
          1062.0,
          516.0,
          1071.0,
          515.0,
          1075.0,
          521.0,
          1079.0,
          518.0,
          1083.0,
          512.0,
          1081.0,
          519.0,
          1087.0,
          522.0,
          1081.0,
          528.0,
          1082.0,
          525.0,
          1093.0,
          516.0,
          1103.0,
          515.0,
          1127.0,
          530.0,
          1126.0,
          552.0,
          1117.0,
          556.0,
          1119.0,
          556.0,
          1122.0,
          550.0,
          1126.0,
          545.0,
          1125.0,
          541.0,
          1130.0,
          538.0,
          1128.0,
          537.0,
          1133.0,
          532.0,
          1132.0,
          519.0,
          1139.0,
          515.0,
          1147.0,
          521.0,
          1158.0,
          520.0,
          1161.0,
          515.0,
          1161.0,
          519.0,
          1169.0,
          569.0,
          1168.0,
          573.0,
          1164.0,
          576.0,
          1166.0,
          579.0,
          1164.0,
          583.0,
          1168.0,
          600.0,
          1154.0,
          614.0,
          1158.0,
          623.0,
          1146.0,
          632.0,
          1146.0,
          634.0,
          1148.0,
          632.0,
          1155.0,
          637.0,
          1145.0,
          647.0,
          1140.0,
          651.0,
          1146.0,
          660.0,
          1142.0,
          664.0,
          1147.0,
          672.0,
          1143.0,
          677.0,
          1147.0,
          680.0,
          1142.0,
          676.0,
          1137.0,
          690.0,
          1128.0,
          690.0,
          1121.0,
          680.0,
          1106.0,
          680.0,
          1099.0,
          683.0,
          1097.0,
          681.0,
          1081.0,
          666.0,
          1053.0,
          657.0,
          1048.0,
          628.0,
          1054.0,
          622.0,
          1052.0,
          625.0,
          1060.0,
          622.0,
          1064.0,
          610.0,
          1051.0,
          608.0,
          1061.0,
          611.0,
          1064.0,
          618.0,
          1064.0,
          622.0,
          1069.0,
          622.0,
          1078.0,
          613.0,
          1085.0,
          605.0,
          1084.0,
          599.0,
          1076.0,
          600.0,
          1070.0,
          593.0,
          1069.0,
          593.0,
          1064.0,
          588.0,
          1062.0,
          586.0,
          1052.0,
          581.0,
          1047.0,
          585.0,
          1034.0,
          563.0,
          1034.0,
          563.0,
          1039.0,
          556.0,
          1042.0,
          554.0,
          1050.0,
          549.0,
          1052.0,
          546.0,
          1058.0,
          533.0,
          1051.0,
          520.0,
          1052.0
        ]
      ]
    },
    {
      "instance_id": 7,
      "class_id": 3,
      "class_name": "Type_4",
      "score": 0.8223021626472473,
      "source": "teacher+classical",
      "box": [
        233,
        874,
        462,
        1031
      ],
      "area": 25019,
      "polygons": [
        [
          233.0,
          941.0,
          233.0,
          961.0,
          245.0,
          962.0,
          259.0,
          976.0,
          260.0,
          1011.0,
          276.0,
          1016.0,
          286.0,
          1026.0,
          286.0,
          1030.0,
          397.0,
          1030.0,
          399.0,
          1024.0,
          425.0,
          1007.0,
          431.0,
          998.0,
          441.0,
          993.0,
          447.0,
          984.0,
          457.0,
          980.0,
          461.0,
          974.0,
          461.0,
          956.0,
          447.0,
          956.0,
          440.0,
          972.0,
          433.0,
          975.0,
          433.0,
          968.0,
          427.0,
          962.0,
          434.0,
          956.0,
          434.0,
          948.0,
          412.0,
          940.0,
          420.0,
          926.0,
          434.0,
          927.0,
          431.0,
          922.0,
          426.0,
          924.0,
          413.0,
          914.0,
          426.0,
          912.0,
          435.0,
          897.0,
          424.0,
          897.0,
          421.0,
          891.0,
          423.0,
          882.0,
          411.0,
          878.0,
          409.0,
          874.0,
          356.0,
          874.0,
          358.0,
          928.0,
          348.0,
          933.0,
          345.0,
          927.0,
          339.0,
          927.0,
          339.0,
          923.0,
          327.0,
          920.0,
          328.0,
          915.0,
          334.0,
          917.0,
          338.0,
          913.0,
          338.0,
          874.0,
          279.0,
          874.0,
          274.0,
          887.0,
          257.0,
          888.0,
          248.0,
          897.0,
          246.0,
          911.0,
          251.0,
          907.0,
          258.0,
          907.0,
          258.0,
          918.0,
          265.0,
          921.0,
          264.0,
          927.0,
          275.0,
          931.0,
          280.0,
          939.0
        ]
      ]
    },
    {
      "instance_id": 8,
      "class_id": 0,
      "class_name": "Type_1",
      "score": 0.8061079978942871,
      "source": "teacher+classical",
      "box": [
        616,
        664,
        711,
        818
      ],
      "area": 10798,
      "polygons": [
        [
          616.0,
          664.0,
          616.0,
          698.0,
          622.0,
          699.0,
          626.0,
          705.0,
          626.0,
          709.0,
          629.0,
          712.0,
          630.0,
          711.0,
          633.0,
          713.0,
          632.0,
          718.0,
          626.0,
          718.0,
          629.0,
          725.0,
          625.0,
          729.0,
          616.0,
          732.0,
          616.0,
          817.0,
          620.0,
          813.0,
          623.0,
          815.0,
          623.0,
          817.0,
          710.0,
          817.0,
          710.0,
          682.0,
          667.0,
          682.0,
          661.0,
          684.0,
          656.0,
          682.0,
          653.0,
          684.0,
          649.0,
          681.0,
          648.0,
          675.0,
          645.0,
          677.0,
          638.0,
          675.0,
          634.0,
          671.0,
          631.0,
          664.0
        ]
      ]
    },
    {
      "instance_id": 9,
      "class_id": 3,
      "class_name": "Type_4",
      "score": 0.7987827658653259,
      "source": "teacher+classical",
      "box": [
        500,
        766,
        734,
        914
      ],
      "area": 23754,
      "polygons": [
        [
          500.0,
          810.0,
          500.0,
          840.0,
          527.0,
          848.0,
          530.0,
          852.0,
          527.0,
          863.0,
          533.0,
          865.0,
          532.0,
          874.0,
          538.0,
          874.0,
          539.0,
          879.0,
          542.0,
          877.0,
          546.0,
          880.0,
          550.0,
          875.0,
          554.0,
          881.0,
          571.0,
          879.0,
          580.0,
          883.0,
          592.0,
          900.0,
          589.0,
          913.0,
          733.0,
          913.0,
          733.0,
          896.0,
          713.0,
          896.0,
          706.0,
          890.0,
          705.0,
          871.0,
          717.0,
          861.0,
          711.0,
          827.0,
          710.0,
          766.0,
          689.0,
          766.0,
          685.0,
          772.0,
          693.0,
          779.0,
          692.0,
          782.0,
          667.0,
          781.0,
          662.0,
          790.0,
          641.0,
          788.0,
          635.0,
          782.0,
          635.0,
          776.0,
          639.0,
          773.0,
          637.0,
          766.0,
          545.0,
          766.0,
          542.0,
          771.0,
          523.0,
          779.0,
          568.0,
          796.0,
          565.0,
          803.0,
          561.0,
          798.0,
          558.0,
          800.0,
          548.0,
          793.0,
          544.0,
          797.0,
          541.0,
          791.0,
          537.0,
          795.0,
          532.0,
          793.0,
          528.0,
          810.0,
          543.0,
          817.0,
          554.0,
          816.0,
          555.0,
          819.0,
          549.0,
          825.0,
          536.0,
          826.0,
          531.0,
          820.0,
          520.0,
          821.0,
          506.0,
          810.0
        ]
      ]
    },
    {
      "instance_id": 10,
      "class_id": 2,
      "class_name": "Type_3",
      "score": 0.7270021438598633,
      "source": "teacher+classical",
      "box": [
        616,
        592,
        774,
        765
      ],
      "area": 17647,
      "polygons": [
        [
          716.0,
          592.0,
          700.0,
          594.0,
          693.0,
          601.0,
          683.0,
          601.0,
          673.0,
          607.0,
          668.0,
          603.0,
          661.0,
          607.0,
          636.0,
          603.0,
          616.0,
          605.0,
          616.0,
          714.0,
          626.0,
          711.0,
          630.0,
          706.0,
          635.0,
          712.0,
          632.0,
          724.0,
          628.0,
          726.0,
          625.0,
          724.0,
          622.0,
          729.0,
          616.0,
          730.0,
          616.0,
          764.0,
          636.0,
          764.0,
          629.0,
          756.0,
          630.0,
          747.0,
          649.0,
          740.0,
          647.0,
          734.0,
          650.0,
          732.0,
          650.0,
          722.0,
          653.0,
          720.0,
          651.0,
          711.0,
          654.0,
          708.0,
          651.0,
          703.0,
          653.0,
          698.0,
          651.0,
          687.0,
          655.0,
          684.0,
          661.0,
          687.0,
          661.0,
          691.0,
          669.0,
          692.0,
          670.0,
          697.0,
          667.0,
          700.0,
          674.0,
          703.0,
          668.0,
          714.0,
          671.0,
          717.0,
          673.0,
          734.0,
          667.0,
          738.0,
          682.0,
          742.0,
          694.0,
          749.0,
          698.0,
          754.0,
          698.0,
          759.0,
          693.0,
          764.0,
          713.0,
          764.0,
          720.0,
          757.0,
          733.0,
          753.0,
          731.0,
          747.0,
          740.0,
          744.0,
          746.0,
          749.0,
          757.0,
          742.0,
          764.0,
          741.0,
          766.0,
          736.0,
          761.0,
          730.0,
          773.0,
          725.0,
          770.0,
          714.0,
          747.0,
          679.0,
          742.0,
          676.0,
          733.0,
          658.0,
          716.0,
          641.0,
          715.0,
          634.0,
          732.0,
          615.0,
          732.0,
          611.0
        ]
      ]
    },
    {
      "instance_id": 11,
      "class_id": 1,
      "class_name": "Type_2",
      "score": 0.6504219770431519,
      "source": "teacher+classical",
      "box": [
        259,
        754,
        643,
        977
      ],
      "area": 53508,
      "polygons": [
        [
          259.0,
          976.0,
          357.0,
          976.0,
          353.0,
          953.0,
          388.0,
          951.0,
          392.0,
          976.0,
          422.0,
          976.0,
          434.0,
          949.0,
          444.0,
          956.0,
          438.0,
          976.0,
          462.0,
          976.0,
          496.0,
          947.0,
          526.0,
          959.0,
          554.0,
          949.0,
          575.0,
          965.0,
          594.0,
          949.0,
          596.0,
          934.0,
          562.0,
          914.0,
          560.0,
          891.0,
          554.0,
          896.0,
          538.0,
          883.0,
          528.0,
          890.0,
          526.0,
          874.0,
          580.0,
          883.0,
          590.0,
          906.0,
          570.0,
          906.0,
          582.0,
          923.0,
          591.0,
          926.0,
          601.0,
          915.0,
          617.0,
          920.0,
          624.0,
          875.0,
          605.0,
          866.0,
          605.0,
          851.0,
          583.0,
          828.0,
          593.0,
          825.0,
          603.0,
          805.0,
          642.0,
          818.0,
          636.0,
          764.0,
          629.0,
          754.0,
          573.0,
          754.0,
          523.0,
          778.0,
          567.0,
          795.0,
          565.0,
          803.0,
          541.0,
          791.0,
          517.0,
          792.0,
          517.0,
          779.0,
          496.0,
          787.0,
          490.0,
          779.0,
          478.0,
          779.0,
          469.0,
          754.0,
          354.0,
          754.0,
          351.0,
          799.0,
          339.0,
          798.0,
          339.0,
          790.0,
          331.0,
          794.0,
          337.0,
          779.0,
          321.0,
          778.0,
          318.0,
          783.0,
          331.0,
          790.0,
          309.0,
          787.0,
          304.0,
          813.0,
          332.0,
          824.0,
          335.0,
          817.0,
          349.0,
          819.0,
          358.0,
          828.0,
          358.0,
          928.0,
          348.0,
          933.0,
          327.0,
          920.0,
          338.0,
          913.0,
          338.0,
          836.0,
          306.0,
          834.0,
          305.0,
          859.0,
          286.0,
          881.0,
          288.0,
          896.0,
          305.0,
          908.0,
          305.0,
          933.0,
          259.0,
          941.0
        ]
      ]
    },
    {
      "instance_id": 12,
      "class_id": 1,
      "class_name": "Type_2",
      "score": 0.529119074344635,
      "source": "teacher+classical",
      "box": [
        270,
        881,
        609,
        1165
      ],
      "area": 66188,
      "polygons": [
        [
          270.0,
          941.0,
          270.0,
          1019.0,
          287.0,
          1027.0,
          286.0,
          1037.0,
          270.0,
          1052.0,
          270.0,
          1128.0,
          277.0,
          1128.0,
          290.0,
          1111.0,
          308.0,
          1107.0,
          313.0,
          1112.0,
          310.0,
          1119.0,
          316.0,
          1117.0,
          323.0,
          1123.0,
          313.0,
          1125.0,
          322.0,
          1131.0,
          364.0,
          1129.0,
          373.0,
          1133.0,
          397.0,
          1157.0,
          397.0,
          1164.0,
          501.0,
          1164.0,
          491.0,
          1150.0,
          461.0,
          1146.0,
          474.0,
          1126.0,
          488.0,
          1132.0,
          493.0,
          1125.0,
          513.0,
          1130.0,
          553.0,
          1117.0,
          556.0,
          1122.0,
          544.0,
          1126.0,
          547.0,
          1132.0,
          557.0,
          1136.0,
          568.0,
          1130.0,
          579.0,
          1132.0,
          587.0,
          1121.0,
          581.0,
          1107.0,
          588.0,
          1099.0,
          607.0,
          1092.0,
          608.0,
          1087.0,
          583.0,
          1058.0,
          588.0,
          1012.0,
          581.0,
          999.0,
          582.0,
          989.0,
          566.0,
          975.0,
          590.0,
          953.0,
          582.0,
          944.0,
          584.0,
          929.0,
          572.0,
          925.0,
          542.0,
          898.0,
          523.0,
          909.0,
          529.0,
          920.0,
          525.0,
          937.0,
          502.0,
          949.0,
          492.0,
          933.0,
          496.0,
          923.0,
          490.0,
          914.0,
          460.0,
          909.0,
          453.0,
          916.0,
          441.0,
          917.0,
          445.0,
          922.0,
          442.0,
          926.0,
          426.0,
          924.0,
          412.0,
          915.0,
          410.0,
          905.0,
          419.0,
          881.0,
          356.0,
          881.0,
          357.0,
          929.0,
          348.0,
          933.0,
          339.0,
          923.0,
          312.0,
          915.0,
          302.0,
          936.0
        ]
      ]
    },
    {
      "instance_id": 13,
      "class_id": 3,
      "class_name": "Type_4",
      "score": 0.34179872274398804,
      "source": "teacher+classical",
      "box": [
        368,
        833,
        598,
        984
      ],
      "area": 21157,
      "polygons": [
        [
          597.0,
          846.0,
          566.0,
          833.0,
          494.0,
          833.0,
          495.0,
          838.0,
          518.0,
          844.0,
          524.0,
          851.0,
          512.0,
          855.0,
          502.0,
          849.0,
          484.0,
          850.0,
          480.0,
          845.0,
          461.0,
          852.0,
          476.0,
          864.0,
          486.0,
          863.0,
          490.0,
          870.0,
          502.0,
          872.0,
          498.0,
          877.0,
          495.0,
          874.0,
          489.0,
          877.0,
          480.0,
          875.0,
          476.0,
          869.0,
          435.0,
          862.0,
          431.0,
          851.0,
          414.0,
          852.0,
          429.0,
          857.0,
          420.0,
          875.0,
          407.0,
          866.0,
          412.0,
          852.0,
          368.0,
          842.0,
          368.0,
          929.0,
          378.0,
          930.0,
          385.0,
          918.0,
          399.0,
          924.0,
          395.0,
          937.0,
          399.0,
          947.0,
          389.0,
          955.0,
          392.0,
          983.0,
          418.0,
          983.0,
          430.0,
          960.0,
          438.0,
          971.0,
          435.0,
          983.0,
          452.0,
          983.0,
          469.0,
          966.0,
          480.0,
          962.0,
          491.0,
          964.0,
          497.0,
          970.0,
          519.0,
          963.0,
          524.0,
          966.0,
          528.0,
          962.0,
          539.0,
          966.0,
          546.0,
          961.0,
          542.0,
          957.0,
          546.0,
          949.0,
          558.0,
          951.0,
          560.0,
          956.0,
          551.0,
          958.0,
          562.0,
          964.0,
          575.0,
          965.0,
          590.0,
          952.0,
          578.0,
          944.0,
          570.0,
          931.0,
          570.0,
          922.0,
          558.0,
          909.0,
          561.0,
          892.0,
          554.0,
          896.0,
          538.0,
          883.0,
          530.0,
          891.0,
          525.0,
          878.0,
          529.0,
          872.0,
          538.0,
          874.0,
          539.0,
          879.0,
          546.0,
          880.0,
          550.0,
          875.0,
          554.0,
          881.0,
          568.0,
          881.0,
          571.0,
          871.0,
          566.0,
          865.0,
          573.0,
          862.0,
          597.0,
          870.0
        ]
      ]
    }
  ]
}
