{
  "crowded": false,
  "objects": [
    {
      "class_id": 0,
      "box": [
        173,
        272,
        450,
        632
      ]
    },
    {
      "class_id": 1,
      "box": [
        16,
        81,
        987,
        483
      ]
    },
    {
      "class_id": 1,
      "box": [
        413,
        342,
        811,
        701
      ]
    },
    {
      "class_id": 3,
      "box": [
        21,
        1180,
        589,
        1652
      ]
    },
    {
      "class_id": 3,
      "box": [
        276,
        439,
        994,
        1131
      ]
    },
    {
      "class_id": 4,
      "box": [
        220,
        1367,
        456,
        1599
      ]
    },
    {
      "class_id": 1,
      "box": [
        541,
        910,
        1071,
        1439
      ]
    },
    {
      "class_id": 3,
      "box": [
        449,
        682,
        1142,
        1368
      ]
    },
    {
      "class_id": 4,
      "box": [
        176,
        626,
        823,
        1308
      ]
    },
    {
      "class_id": 3,
      "box": [
        9,
        764,
        796,
        1653
      ]
    },
    {
      "class_id": 3,
      "box": [
        412,
        275,
        997,
        749
      ]
    },
    {
      "class_id": 0,
      "box": [
        498,
        877,
        649,
        995
      ]
    },
    {
      "class_id": 0,
      "box": [
        231,
        1285,
        426,
        1488
      ]
    },
    {
      "class_id": 4,
      "box": [
        401,
        243,
        934,
        932
      ]
    }
  ]
}
