{
  "crowded": false,
  "objects": [
    {
      "class_id": 0,
      "box": [
        256,
        748,
        799,
        1267
      ]
    },
    {
      "class_id": 3,
      "box": [
        28,
        229,
        817,
        875
      ]
    },
    {
      "class_id": 0,
      "box": [
        538,
        906,
        1129,
        1461
      ]
    },
    {
      "class_id": 0,
      "box": [
        691,
        451,
        1069,
        702
      ]
    },
    {
      "class_id": 4,
      "box": [
        61,
        1406,
        289,
        1664
      ]
    },
    {
      "class_id": 3,
      "box": [
        117,
        14,
        1005,
        889
      ]
    },
    {
      "class_id": 0,
      "box": [
        91,
        489,
        496,
        846
      ]
    },
    {
      "class_id": 1,
      "box": [
        163,
        132,
        864,
        1154
      ]
    },
    {
      "class_id": 3,
      "box": [
        59,
        108,
        936,
        949
      ]
    },
    {
      "class_id": 3,
      "box": [
        678,
        880,
        1154,
        1110
      ]
    },
    {
      "class_id": 4,
      "box": [
        343,
        773,
        927,
        1409
      ]
    },
    {
      "class_id": 2,
      "box": [
        29,
        493,
        833,
        1182
      ]
    },
    {
      "class_id": 3,
      "box": [
        659,
        1124,
        874,
        1333
      ]
    },
    {
      "class_id": 3,
      "box": [
        337,
        844,
        1157,
        1548
      ]
    },
    {
      "class_id": 3,
      "box": [
        792,
        8,
        1029,
        225
      ]
    },
    {
      "class_id": 3,
      "box": [
        169,
        237,
        914,
        863
      ]
    },
    {
      "class_id": 2,
      "box": [
        305,
        655,
        756,
        1078
      ]
    },
    {
      "class_id": 3,
      "box": [
        113,
        450,
        393,
        730
      ]
    },
    {
      "class_id": 3,
      "box": [
        417,
        578,
        1196,
        1367
      ]
    }
  ]
}
